sphinxcontrib/htmlhelp/__init__.py
sphinxcontrib/htmlhelp/locales/sphinxcontrib.htmlhelp.pot
sphinxcontrib/htmlhelp/locales/.tx/config
sphinxcontrib/htmlhelp/locales/ar/LC_MESSAGES/sphinxcontrib.htmlhelp.mo
sphinxcontrib/htmlhelp/locales/ar/LC_MESSAGES/sphinxcontrib.htmlhelp.po
sphinxcontrib/htmlhelp/locales/bg/LC_MESSAGES/sphinxcontrib.htmlhelp.mo
sphinxcontrib/htmlhelp/locales/bg/LC_MESSAGES/sphinxcontrib.htmlhelp.po
sphinxcontrib/htmlhelp/locales/bn/LC_MESSAGES/sphinxcontrib.htmlhelp.mo
sphinxcontrib/htmlhelp/locales/bn/LC_MESSAGES/sphinxcontrib.htmlhelp.po
sphinxcontrib/htmlhelp/locales/ca/LC_MESSAGES/sphinxcontrib.htmlhelp.mo
sphinxcontrib/htmlhelp/locales/ca/LC_MESSAGES/sphinxcontrib.htmlhelp.po
sphinxcontrib/htmlhelp/locales/cak/LC_MESSAGES/sphinxcontrib.htmlhelp.mo
sphinxcontrib/htmlhelp/locales/cak/LC_MESSAGES/sphinxcontrib.htmlhelp.po
sphinxcontrib/htmlhelp/locales/cs/LC_MESSAGES/sphinxcontrib.htmlhelp.mo
sphinxcontrib/htmlhelp/locales/cs/LC_MESSAGES/sphinxcontrib.htmlhelp.po
sphinxcontrib/htmlhelp/locales/cy/LC_MESSAGES/sphinxcontrib.htmlhelp.mo
sphinxcontrib/htmlhelp/locales/cy/LC_MESSAGES/sphinxcontrib.htmlhelp.po
sphinxcontrib/htmlhelp/locales/da/LC_MESSAGES/sphinxcontrib.htmlhelp.mo
sphinxcontrib/htmlhelp/locales/da/LC_MESSAGES/sphinxcontrib.htmlhelp.po
sphinxcontrib/htmlhelp/locales/de/LC_MESSAGES/sphinxcontrib.htmlhelp.mo
sphinxcontrib/htmlhelp/locales/de/LC_MESSAGES/sphinxcontrib.htmlhelp.po
sphinxcontrib/htmlhelp/locales/el/LC_MESSAGES/sphinxcontrib.htmlhelp.mo
sphinxcontrib/htmlhelp/locales/el/LC_MESSAGES/sphinxcontrib.htmlhelp.po
sphinxcontrib/htmlhelp/locales/eo/LC_MESSAGES/sphinxcontrib.htmlhelp.mo
sphinxcontrib/htmlhelp/locales/eo/LC_MESSAGES/sphinxcontrib.htmlhelp.po
sphinxcontrib/htmlhelp/locales/es/LC_MESSAGES/sphinxcontrib.htmlhelp.mo
sphinxcontrib/htmlhelp/locales/es/LC_MESSAGES/sphinxcontrib.htmlhelp.po
sphinxcontrib/htmlhelp/locales/et/LC_MESSAGES/sphinxcontrib.htmlhelp.mo
sphinxcontrib_htmlhelp-2.0.2.dist-info/LICENSE
sphinxcontrib_htmlhelp-2.0.2.dist-info/WHEEL
sphinxcontrib_htmlhelp-2.0.2.dist-info/METADATA
sphinxcontrib_htmlhelp-2.0.2.dist-info/RECORD
